scrc/pygamepro/__init__.py
scrc/pygamepro/pac.py
pygamepro-0.1.3.dist-info/METADATA
pygamepro-0.1.3.dist-info/WHEEL
pygamepro-0.1.3.dist-info/licenses/LICENCE
pygamepro-0.1.3.dist-info/RECORD
